uwudu/__init__.py
uwudu/cli.py
uwudu/file.py
uwudu/table.py
uwudu-1.0.1.dist-info/LICENSE
uwudu-1.0.1.dist-info/METADATA
uwudu-1.0.1.dist-info/WHEEL
uwudu-1.0.1.dist-info/entry_points.txt
uwudu-1.0.1.dist-info/top_level.txt
uwudu-1.0.1.dist-info/RECORD
