Metadata-Version: 2.1
Name: uwudu
Version: 1.0.1
Summary: your cli todo list manager (U w U)
Keywords: cli,todo,uwu,todo list,python,python cli
License-File: LICENSE
Requires-Dist: click
Requires-Dist: prettytable
